fc_xd_bigdata.py
fc_bigdataysk-2.0.dist-info/METADATA
fc_bigdataysk-2.0.dist-info/WHEEL
fc_bigdataysk-2.0.dist-info/top_level.txt
fc_bigdataysk-2.0.dist-info/RECORD
