Metadata-Version: 2.1
Name: fc-bigdataysk
Version: 2.0
Summary: 杨帅康
Home-page: UNKNOWN
Author: 大数据3
Author-email: fc@bigdata.com
License: UNKNOWN
Platform: UNKNOWN
